{
    "model_name": "parameterless_knn_convex_hull_intra_margin_clustering",
    "dataset": "titanic",
    "hyperparameters": {
        "metric": "convex_hull_intra",
        "n_optimizer_calls": 10,
        "support_samples_method": "margin_clustering"
    },
    "metrics": {
        "accuracy_mean": 0.7418144450968879,
        "accuracy_std": 0.02455871813526178,
        "train_time_mean": 0.8116681699997571,
        "train_time_std": 0.11358077426818541,
        "predict_time_mean": 0.009267490000274848,
        "predict_time_std": 0.0017848738781940253
    }
}