{
    "model_name": "parameterless_knn_opposite_hyperplane_gabriel_graph",
    "dataset": "titanic",
    "hyperparameters": {
        "metric": "opposite_hyperplane",
        "n_optimizer_calls": 10,
        "support_samples_method": "gabriel_graph"
    },
    "metrics": {
        "accuracy_mean": 0.7738696418085731,
        "accuracy_std": 0.030973233704269323,
        "train_time_mean": 34.18369210999954,
        "train_time_std": 1.3500239166466077,
        "predict_time_mean": 0.01140305000008084,
        "predict_time_std": 0.0017507988382271396
    }
}