{
    "model_name": "parameterless_knn_opposite_hyperplane_margin_clustering",
    "dataset": "heart_disease",
    "hyperparameters": {
        "metric": "opposite_hyperplane",
        "n_optimizer_calls": 10,
        "support_samples_method": "margin_clustering"
    },
    "metrics": {
        "accuracy_mean": 0.5710752688172043,
        "accuracy_std": 0.06006981331719015,
        "train_time_mean": 0.24704347999977472,
        "train_time_std": 0.03606778437140551,
        "predict_time_mean": 0.0017517200005386258,
        "predict_time_std": 0.0002976270641945154
    }
}