{
    "model_name": "parameterless_knn_silhouette_hnbf",
    "dataset": "diabetes_pima",
    "hyperparameters": {
        "metric": "silhouette",
        "n_optimizer_calls": 10,
        "support_samples_method": "hnbf"
    },
    "metrics": {
        "accuracy_mean": 0.6797163362952836,
        "accuracy_std": 0.03760439565662923,
        "train_time_mean": 0.3863510300001508,
        "train_time_std": 0.06541285733922193,
        "predict_time_mean": 0.0037390000001323643,
        "predict_time_std": 0.00037538530892971156
    }
}